markdown_github_alerts/__init__.py
markdown_github_alerts/icons.py
markdown_github_alerts-0.2.dist-info/LICENSE
markdown_github_alerts-0.2.dist-info/METADATA
markdown_github_alerts-0.2.dist-info/WHEEL
markdown_github_alerts-0.2.dist-info/top_level.txt
markdown_github_alerts-0.2.dist-info/RECORD
